{
  "folder": null,
  "name": "Winter Sleep",
  "type": "spell",
  "_id": "OjNmCyxldoIkZDhf",
  "img": "icons/svg/item-bag.svg",
  "system": {
    "description": "<p>The targets feels the lethargy of winter overcome them, and they fall asleep. On the targets’ next action and every action thereafter, they may attempt to wake up by rolling a [STR + SPI] check with a target number of 6. If they succeed, they awaken, but their turn is over. If a sleeping creature takes any damage, they immediately wake up.</p>",
    "magicType": "winter",
    "spellType": "normal",
    "manaCost": 4,
    "duration": 0,
    "durationUnit": "instant",
    "target": "1 Area",
    "range": "All Areas",
    "rolls": [],
    "spellLevel": "low"
  },
  "effects": [],
  "flags": {},
  "_stats": {
    "systemId": "ryuutama",
    "systemVersion": "0.0.2",
    "coreVersion": "11.315",
    "createdTime": 1708989602245,
    "modifiedTime": 1708990177404,
    "lastModifiedBy": "YGXn48bHOBjcgvWf"
  },
  "sort": 0,
  "ownership": {
    "default": 0,
    "YGXn48bHOBjcgvWf": 3
  },
  "_key": "!items!OjNmCyxldoIkZDhf"
}
